espresso/Context.py
espresso/Evaluator.py
espresso/Lexer.py
espresso/Parser.py
espresso/__init__.py
espresso/exceptions.py
espresso/utils.py
tests/__init__.py
tests/test_evaluator.py
tests/test_lexer.py
tests/test_parser.py
python_espresso-1.8.4.dist-info/LICENSE
python_espresso-1.8.4.dist-info/METADATA
python_espresso-1.8.4.dist-info/WHEEL
python_espresso-1.8.4.dist-info/top_level.txt
python_espresso-1.8.4.dist-info/RECORD
