Metadata-Version: 2.1
Name: python-espresso
Version: 1.8.4
Summary: A tiny type-safe expression parser in Python
Home-page: https://github.com/aadv1k/python-espresso
Author: Aadvik P
Author-email: aadv1k@outlook.com
License: MIT
License-File: LICENSE
